<?xml version="1.0" encoding="UTF-8"?>
<QCARConfig xmlns:xsi="http://www.w3.org/2001/XMLSchema-instance" xsi:noNamespaceSchemaLocation="qcar_config.xsd">
  <Tracking>
    <ImageTarget name="PAGE_26" size="1.000000 1.350127" />
    <ImageTarget name="PAGE_33" size="1.000000 1.350127" />
    <ImageTarget name="PAGE_9" size="1.000000 1.350127" />
    <ImageTarget name="PAGE_8" size="1.000000 1.350127" />
    <ImageTarget name="PAGE_7" size="1.000000 1.350127" />
    <ImageTarget name="PAGE_21" size="1.000000 1.350127" />
    <ImageTarget name="PAGE_18" size="1.000000 1.350127" />
    <ImageTarget name="_PAGE_1" size="1.000000 1.000000" />
    <ImageTarget name="PAGE17_img" size="1024.000000 1024.000000" />
    <ImageTarget name="Marker-00" size="1.000000 1.000000" />
  </Tracking>
</QCARConfig>
